centricube_langchain/__init__.py
centricube_langchain/text_splitter.py
centricube_langchain/agents/__init__.py
centricube_langchain/agents/chatglm_functions_agent/__init__.py
centricube_langchain/agents/chatglm_functions_agent/base.py
centricube_langchain/agents/chatglm_functions_agent/output_parser.py
centricube_langchain/agents/chatglm_functions_agent/prompt.py
centricube_langchain/agents/llm_functions_agent/__init__.py
centricube_langchain/agents/llm_functions_agent/base.py
centricube_langchain/autogen_role/__init__.py
centricube_langchain/autogen_role/assistant.py
centricube_langchain/autogen_role/custom.py
centricube_langchain/autogen_role/groupchat_manager.py
centricube_langchain/autogen_role/user.py
centricube_langchain/chains/__init__.py
centricube_langchain/chains/loader_output.py
centricube_langchain/chains/transform.py
centricube_langchain/chains/autogen/__init__.py
centricube_langchain/chains/autogen/auto_gen.py
centricube_langchain/chains/combine_documents/__init__.py
centricube_langchain/chains/combine_documents/stuff.py
centricube_langchain/chains/conversational_retrieval/__init__.py
centricube_langchain/chains/conversational_retrieval/base.py
centricube_langchain/chains/qa_generation/__init__.py
centricube_langchain/chains/qa_generation/base.py
centricube_langchain/chains/qa_generation/base_v2.py
centricube_langchain/chains/qa_generation/prompt.py
centricube_langchain/chains/qa_generation/prompt_v2.py
centricube_langchain/chains/question_answering/__init__.py
centricube_langchain/chains/retrieval/__init__.py
centricube_langchain/chains/retrieval/retrieval_chain.py
centricube_langchain/chains/router/__init__.py
centricube_langchain/chains/router/multi_rule.py
centricube_langchain/chains/router/rule_router.py
centricube_langchain/chat_models/__init__.py
centricube_langchain/chat_models/host_llm.py
centricube_langchain/chat_models/minimax.py
centricube_langchain/chat_models/proxy_llm.py
centricube_langchain/chat_models/qwen.py
centricube_langchain-1.3.0.dist-info/METADATA
centricube_langchain-1.3.0.dist-info/WHEEL
centricube_langchain-1.3.0.dist-info/top_level.txt
centricube_langchain-1.3.0.dist-info/RECORD
