Metadata-Version: 2.4
Name: centricube_langchain
Version: 1.3.0
Summary: centricube langchain modules
Home-page: https://github.com/cicit/centricube
Author: CICIT
Author-email: jweelee@qq.com
License: Apache 2.0
Classifier: Programming Language :: Python :: 3
Classifier: Programming Language :: Python :: 3.6
Classifier: Programming Language :: Python :: 3.7
Classifier: Programming Language :: Python :: 3.8
Classifier: Programming Language :: Python :: 3.9
Classifier: License :: OSI Approved :: Apache Software License
Classifier: Operating System :: OS Independent
Requires-Python: >=3.6
Requires-Dist: langchain==0.3.*
Requires-Dist: zhipuai
Requires-Dist: websocket-client
Requires-Dist: elasticsearch
Requires-Dist: opencv-python==4.5.5.64
Requires-Dist: Pillow==9.5.0
Requires-Dist: centricube_pyautogen
Requires-Dist: jieba==0.42.1
Requires-Dist: pydantic
Requires-Dist: pymupdf
Requires-Dist: shapely==2.0.2
Requires-Dist: filetype==1.2.0
Requires-Dist: langgraph==0.3.*
Requires-Dist: openai==1.*
Requires-Dist: langchain_openai==0.3.*
Requires-Dist: llama-index==0.9.48
Requires-Dist: centricube_ragas==1.*
Dynamic: author
Dynamic: author-email
Dynamic: classifier
Dynamic: description
Dynamic: description-content-type
Dynamic: home-page
Dynamic: license
Dynamic: requires-dist
Dynamic: requires-python
Dynamic: summary
